djontainu/__init__.py
djontainu/cli.py
djontainu-0.1.1.dist-info/LICENSE
djontainu-0.1.1.dist-info/METADATA
djontainu-0.1.1.dist-info/WHEEL
djontainu-0.1.1.dist-info/entry_points.txt
djontainu-0.1.1.dist-info/top_level.txt
djontainu-0.1.1.dist-info/RECORD
