Metadata-Version: 2.1
Name: djontainu
Version: 0.1.1
Summary: Simple package to help manage python (mostly django) docker containers.
Author-email: Nommu Moose <moose@nommumail.co.uk>
Classifier: Programming Language :: Python :: 3
Classifier: License :: OSI Approved :: MIT License
Classifier: Operating System :: OS Independent
License-File: LICENSE
Requires-Dist: click
